messengercli/__init__.py
messengercli/command_line.py
messengercli/messenger.py
messengercli/updater.py
elm_messenger-0.6.0.dist-info/METADATA
elm_messenger-0.6.0.dist-info/WHEEL
elm_messenger-0.6.0.dist-info/entry_points.txt
elm_messenger-0.6.0.dist-info/top_level.txt
elm_messenger-0.6.0.dist-info/RECORD
