Metadata-Version: 2.4
Name: elm-messenger
Version: 0.6.0
Summary: The Messenger toolkit for Elm
Author: linsyking
Author-email: linsy_king@sjtu.edu.cn
License: MIT License
Keywords: cli
Requires-Python: >=3.7
Requires-Dist: typer
